{
  "when": "2026-07-07T11:01:59.386Z",
  "overFound": 9,
  "underFound": 1,
  "spreadFound": 2,
  "diag": {
    "url": "https://ttedge.ai/edge-finder",
    "textoLen": 4790,
    "hayPredicciones": true,
    "estrellas": 99,
    "pareceLogin": false,
    "botonesFiltro": [],
    "snippet": " MenuDashboardMatchupsEdge FinderParlaysPlayersHead to HeadMy PicksKnowledge BaseTagsLeaguesTT CupCzech Liga ProSetka CupTT Elite SeriesMy AccountProEdge FinderAdvanced prediction analyticsPredictionsJul 7, 2026Last synced about 6 hours agoSync ScheduleSync H2"
  }
}