{
  "when": "2026-06-22T19:00:12.274Z",
  "overFound": 12,
  "underFound": 0,
  "spreadFound": 0,
  "spreadHighFound": 2,
  "diag": {
    "url": "https://ttedge.ai/edge-finder",
    "textoLen": 4271,
    "hayPredicciones": true,
    "estrellas": 94,
    "pareceLogin": false,
    "botonesFiltro": [],
    "snippet": " MenuDashboardMatchupsEdge FinderParlaysPlayersHead to HeadMy PicksKnowledge BaseTagsLeaguesTT CupCzech Liga ProSetka CupTT Elite SeriesProPlanEdge FinderAdvanced prediction analyticsPredictionsJun 22, 2026Last synced about 6 hours agoSync ScheduleSync H2H (ne"
  }
}