{
  "when": "2026-07-21T08:01:45.094Z",
  "overFound": 3,
  "underFound": 17,
  "spreadFound": 0,
  "diag": {
    "url": "https://ttedge.ai/edge-finder",
    "textoLen": 41021,
    "hayPredicciones": true,
    "estrellas": 284,
    "pareceLogin": false,
    "botonesFiltro": [],
    "snippet": " MenuDashboardMatchupsEdge FinderParlaysPlayersHead to HeadMy PicksKnowledge BaseTagsLeaguesTT CupCzech Liga ProSetka CupTT Elite SeriesMy AccountProEdge FinderAdvanced prediction analyticsPredictionsJul 21, 2026Last synced 2 days agoSync ScheduleSync H2H (nex"
  }
}